{
  "version": "6.1.3",
  "flags": {},
  "shapes": [
    {
      "label": "duckie",
      "points": [
        [
          607.1428571428571,
          203.5714285714286
        ],
        [
          640.0,
          306.1661807580176
        ]
      ],
      "group_id": null,
      "description": "",
      "shape_type": "rectangle",
      "flags": {},
      "mask": null
    },
    {
      "label": "truck",
      "points": [
        [
          221.42857142857144,
          60.71428571428575
        ],
        [
          127.85714285714288,
          4.0523140398818214e-14
        ]
      ],
      "group_id": null,
      "description": "",
      "shape_type": "rectangle",
      "flags": {},
      "mask": null
    }
  ],
  "imagePath": "frame_20260507_135453_777587_0151.jpg",
  "imageData": null,
  "imageHeight": 480,
  "imageWidth": 640
}