{
  "version": "6.1.3",
  "flags": {},
  "shapes": [
    {
      "label": "truck",
      "points": [
        [
          34.28571428571432,
          1.4285714285714692
        ],
        [
          206.42857142857144,
          113.5714285714286
        ]
      ],
      "group_id": null,
      "description": "",
      "shape_type": "rectangle",
      "flags": {},
      "mask": null
    },
    {
      "label": "duckie",
      "points": [
        [
          439.28571428571433,
          35.71428571428575
        ],
        [
          471.42857142857144,
          72.85714285714289
        ]
      ],
      "group_id": null,
      "description": "",
      "shape_type": "rectangle",
      "flags": {},
      "mask": null
    }
  ],
  "imagePath": "frame_20260507_133728_742680_0033.jpg",
  "imageData": null,
  "imageHeight": 480,
  "imageWidth": 640
}